primapy_db/__init__.py
primapy_db-0.1.0.dist-info/WHEEL
primapy_db-0.1.0.dist-info/METADATA
primapy_db-0.1.0.dist-info/RECORD
