Metadata-Version: 2.1
Name: primapy-db
Version: 0.1.0
Summary: Python DB library
Author: Team AMOps
Author-email: amops@prima.it
Requires-Python: >=3.9,<4.0
Classifier: Programming Language :: Python :: 3
Classifier: Programming Language :: Python :: 3.9
Classifier: Programming Language :: Python :: 3.10
